README.rst
setup.py
django_sql_stacktrace.egg-info/PKG-INFO
django_sql_stacktrace.egg-info/SOURCES.txt
django_sql_stacktrace.egg-info/dependency_links.txt
django_sql_stacktrace.egg-info/not-zip-safe
django_sql_stacktrace.egg-info/top_level.txt
sqlstacktrace/__init__.py
sqlstacktrace/replacer.py
sqlstacktrace/stacktrace.py
sqlstacktrace/stacktracecursor.py