Metadata-Version: 1.1
Name: django-sql-stacktrace
Version: 0.2.2
Summary: Pluggable application, which puts a python stack trace in the SQL query as a comment (useful for debugging)
Home-page: http://github.com/adw0rd/django-sql-stacktrace
Author: Mikhail Andreev
Author-email: x11org@gmail.com
License: BSD
Keywords: django,debug,debugging,logger,sql,stack,trace,frame
Platform: UNKNOWN
Classifier: Environment :: Web Environment
Classifier: Programming Language :: Python
Classifier: Programming Language :: SQL
Classifier: Framework :: Django
Classifier: License :: OSI Approved :: BSD License
Classifier: Topic :: Software Development :: Debuggers
Classifier: Topic :: Software Development :: Libraries :: Application Frameworks
Classifier: Topic :: Software Development :: Libraries :: Python Modules
